{"took":1,"timed_out":false,"_shards":{"total":1,"successful":1,"failed":0},"hits":{"total":4,"max_score":null,"hits":[{"_index":"logstash-2015.06.22","_type":"json-tcp","_id":"AU4caI-f72f7YirtUM4_","_score":null,"_source":{"message":"{\"EventReceivedTime\":\"2015-06-22 10:54:47\",\"SourceModuleName\":\"api_trace\",\"SourceModuleType\":\"im_file\",\"Message\":\"{\\\"MetricTypeId\\\":6,\\\"Created\\\":\\\"2015-06-22T17:54:52.179Z\\\",\\\"GlobalUserId\\\":null,\\\"ApplicationId\\\":null,\\\"AnonymousId\\\":\\\"98eaa815-f7d1-4376-93ef-6cafcb57e3ee\\\",\\\"ViewData\\\":null,\\\"SessionData\\\":{\\\"DeviceId\\\":\\\"98EAA815-F7D1-4376-93EF-6CAFCB57E3EE\\\",\\\"AppTypeId\\\":1,\\\"BinaryVersion\\\":\\\"5.14.0\\\",\\\"DeviceOSVersion\\\":\\\"8.3\\\",\\\"MMMInfo\\\":\\\"iPhone6,1\\\"},\\\"BeaconData\\\":null,\\\"UserActionData\\\":null,\\\"CheckpointData\\\":{\\\"Type\\\":\\\"seamlessloginsuccess\\\"},\\\"ErrorData\\\":null,\\\"ContextData\\\":null,\\\"Metadata\\\":null}\",\"environment\":\"prod\",\"app\":\"api\",\"source\":\"trace\",\"region\":\"us\",\"hostname\":\"P-API-01\"}\r","@version":"1","@timestamp":"2015-06-22T17:54:47.000Z","host":"10.208.195.209:61896","type":"json-tcp","EventReceivedTime":"2015-06-22 10:54:47","Message":"{\"MetricTypeId\":6,\"Created\":\"2015-06-22T17:54:52.179Z\",\"GlobalUserId\":null,\"ApplicationId\":null,\"AnonymousId\":\"98eaa815-f7d1-4376-93ef-6cafcb57e3ee\",\"ViewData\":null,\"SessionData\":{\"DeviceId\":\"98EAA815-F7D1-4376-93EF-6CAFCB57E3EE\",\"AppTypeId\":1,\"BinaryVersion\":\"5.14.0\",\"DeviceOSVersion\":\"8.3\",\"MMMInfo\":\"iPhone6,1\"},\"BeaconData\":null,\"UserActionData\":null,\"CheckpointData\":{\"Type\":\"seamlessloginsuccess\"},\"ErrorData\":null,\"ContextData\":null,\"Metadata\":null}","environment":"prod","app":"api","source":"trace","region":"us","hostname":"P-API-01","MetricTypeId":6,"GlobalUserId":null,"ApplicationId":null,"AnonymousId":"98eaa815-f7d1-4376-93ef-6cafcb57e3ee","ViewData":null,"SessionData":{"DeviceId":"98EAA815-F7D1-4376-93EF-6CAFCB57E3EE","AppTypeId":1,"BinaryVersion":"5.14.0","DeviceOSVersion":"8.3","MMMInfo":"iPhone6,1"},"BeaconData":null,"UserActionData":null,"CheckpointData":{"Type":"seamlessloginsuccess"},"ErrorData":null,"ContextData":null,"Metadata":null,"hostip":"10.208.195.209"},"sort":[1434995687000]},{"_index":"logstash-2015.06.22","_type":"json-tcp","_id":"AU4cZbGf72f7YirtUF6n","_score":null,"_source":{"message":"{\"EventReceivedTime\":\"2015-06-22 10:51:46\",\"SourceModuleName\":\"api_trace\",\"SourceModuleType\":\"im_file\",\"Message\":\"{\\\"MetricTypeId\\\":6,\\\"Created\\\":\\\"2015-06-22T17:51:29.849Z\\\",\\\"GlobalUserId\\\":null,\\\"ApplicationId\\\":null,\\\"AnonymousId\\\":\\\"98eaa815-f7d1-4376-93ef-6cafcb57e3ee\\\",\\\"ViewData\\\":null,\\\"SessionData\\\":{\\\"DeviceId\\\":\\\"98EAA815-F7D1-4376-93EF-6CAFCB57E3EE\\\",\\\"AppTypeId\\\":1,\\\"BinaryVersion\\\":\\\"5.14.0\\\",\\\"DeviceOSVersion\\\":\\\"8.3\\\",\\\"MMMInfo\\\":\\\"iPhone6,1\\\"},\\\"BeaconData\\\":null,\\\"UserActionData\\\":null,\\\"CheckpointData\\\":{\\\"Type\\\":\\\"seamlessloginsuccess\\\"},\\\"ErrorData\\\":null,\\\"ContextData\\\":null,\\\"Metadata\\\":null}\",\"environment\":\"prod\",\"app\":\"api\",\"source\":\"trace\",\"region\":\"us\",\"hostname\":\"P-API-04\"}\r","@version":"1","@timestamp":"2015-06-22T17:51:46.000Z","host":"10.208.197.131:54870","type":"json-tcp","EventReceivedTime":"2015-06-22 10:51:46","Message":"{\"MetricTypeId\":6,\"Created\":\"2015-06-22T17:51:29.849Z\",\"GlobalUserId\":null,\"ApplicationId\":null,\"AnonymousId\":\"98eaa815-f7d1-4376-93ef-6cafcb57e3ee\",\"ViewData\":null,\"SessionData\":{\"DeviceId\":\"98EAA815-F7D1-4376-93EF-6CAFCB57E3EE\",\"AppTypeId\":1,\"BinaryVersion\":\"5.14.0\",\"DeviceOSVersion\":\"8.3\",\"MMMInfo\":\"iPhone6,1\"},\"BeaconData\":null,\"UserActionData\":null,\"CheckpointData\":{\"Type\":\"seamlessloginsuccess\"},\"ErrorData\":null,\"ContextData\":null,\"Metadata\":null}","environment":"prod","app":"api","source":"trace","region":"us","hostname":"P-API-04","MetricTypeId":6,"GlobalUserId":null,"ApplicationId":null,"AnonymousId":"98eaa815-f7d1-4376-93ef-6cafcb57e3ee","ViewData":null,"SessionData":{"DeviceId":"98EAA815-F7D1-4376-93EF-6CAFCB57E3EE","AppTypeId":1,"BinaryVersion":"5.14.0","DeviceOSVersion":"8.3","MMMInfo":"iPhone6,1"},"BeaconData":null,"UserActionData":null,"CheckpointData":{"Type":"seamlessloginsuccess"},"ErrorData":null,"ContextData":null,"Metadata":null,"hostip":"10.208.197.131"},"sort":[1434995506000]},{"_index":"logstash-2015.06.22","_type":"json-tcp","_id":"AU4cVmrW72f7YirtThaS","_score":null,"_source":{"message":"{\"EventReceivedTime\":\"2015-06-22 10:35:03\",\"SourceModuleName\":\"api_trace\",\"SourceModuleType\":\"im_file\",\"Message\":\"{\\\"MetricTypeId\\\":6,\\\"Created\\\":\\\"2015-06-22T17:34:34.000Z\\\",\\\"GlobalUserId\\\":\\\"a47130a5-ff17-417d-9676-b4e5d9e0c00e\\\",\\\"ApplicationId\\\":null,\\\"AnonymousId\\\":null,\\\"ViewData\\\":null,\\\"SessionData\\\":{\\\"DeviceId\\\":\\\"36f4a42c-cb96-4416-9e99-33aa49c17cb8\\\",\\\"AppTypeId\\\":3,\\\"BinaryVersion\\\":\\\"5.14.0.0\\\",\\\"DeviceOSVersion\\\":\\\"5.0\\\",\\\"MMMInfo\\\":\\\"kltevl,SM-G900W8,samsung\\\"},\\\"BeaconData\\\":null,\\\"UserActionData\\\":null,\\\"CheckpointData\\\":{\\\"Type\\\":\\\"seamlessloginsuccess\\\"},\\\"ErrorData\\\":null,\\\"ContextData\\\":null,\\\"Metadata\\\":\\\"{}\\\"}\",\"environment\":\"prod\",\"app\":\"api\",\"source\":\"trace\",\"region\":\"us\",\"hostname\":\"P-API-02\"}\r","@version":"1","@timestamp":"2015-06-22T17:35:03.000Z","host":"10.208.193.153:51994","type":"json-tcp","EventReceivedTime":"2015-06-22 10:35:03","Message":"{\"MetricTypeId\":6,\"Created\":\"2015-06-22T17:34:34.000Z\",\"GlobalUserId\":\"a47130a5-ff17-417d-9676-b4e5d9e0c00e\",\"ApplicationId\":null,\"AnonymousId\":null,\"ViewData\":null,\"SessionData\":{\"DeviceId\":\"36f4a42c-cb96-4416-9e99-33aa49c17cb8\",\"AppTypeId\":3,\"BinaryVersion\":\"5.14.0.0\",\"DeviceOSVersion\":\"5.0\",\"MMMInfo\":\"kltevl,SM-G900W8,samsung\"},\"BeaconData\":null,\"UserActionData\":null,\"CheckpointData\":{\"Type\":\"seamlessloginsuccess\"},\"ErrorData\":null,\"ContextData\":null,\"Metadata\":\"{}\"}","environment":"prod","app":"api","source":"trace","region":"us","hostname":"P-API-02","MetricTypeId":6,"GlobalUserId":"a47130a5-ff17-417d-9676-b4e5d9e0c00e","ApplicationId":null,"AnonymousId":null,"ViewData":null,"SessionData":{"DeviceId":"36f4a42c-cb96-4416-9e99-33aa49c17cb8","AppTypeId":3,"BinaryVersion":"5.14.0.0","DeviceOSVersion":"5.0","MMMInfo":"kltevl,SM-G900W8,samsung"},"BeaconData":null,"UserActionData":null,"CheckpointData":{"Type":"seamlessloginsuccess"},"ErrorData":null,"ContextData":null,"Metadata":"{}","hostip":"10.208.193.153","metric.meta":{}},"sort":[1434994503000]},{"_index":"logstash-2015.06.22","_type":"json-tcp","_id":"AU4bGm3y72f7YirtHq53","_score":null,"_source":{"message":"{\"EventReceivedTime\":\"2015-06-22 04:49:55\",\"SourceModuleName\":\"api_trace\",\"SourceModuleType\":\"im_file\",\"Message\":\"{\\\"MetricTypeId\\\":6,\\\"Created\\\":\\\"2015-06-22T11:48:39.108Z\\\",\\\"GlobalUserId\\\":null,\\\"ApplicationId\\\":null,\\\"AnonymousId\\\":\\\"36f362a3-3af8-4c36-8740-5536668ee2d8\\\",\\\"ViewData\\\":null,\\\"SessionData\\\":{\\\"DeviceId\\\":\\\"36F362A3-3AF8-4C36-8740-5536668EE2D8\\\",\\\"AppTypeId\\\":1,\\\"BinaryVersion\\\":\\\"5.14.0\\\",\\\"DeviceOSVersion\\\":\\\"8.2\\\",\\\"MMMInfo\\\":\\\"iPhone5,1\\\"},\\\"BeaconData\\\":null,\\\"UserActionData\\\":null,\\\"CheckpointData\\\":{\\\"Type\\\":\\\"seamlessloginsuccess\\\"},\\\"ErrorData\\\":null,\\\"ContextData\\\":null,\\\"Metadata\\\":null}\",\"environment\":\"prod\",\"app\":\"api\",\"source\":\"trace\",\"region\":\"us\",\"hostname\":\"P-API-02\"}\r","@version":"1","@timestamp":"2015-06-22T11:49:55.000Z","host":"10.208.193.153:51994","type":"json-tcp","EventReceivedTime":"2015-06-22 04:49:55","Message":"{\"MetricTypeId\":6,\"Created\":\"2015-06-22T11:48:39.108Z\",\"GlobalUserId\":null,\"ApplicationId\":null,\"AnonymousId\":\"36f362a3-3af8-4c36-8740-5536668ee2d8\",\"ViewData\":null,\"SessionData\":{\"DeviceId\":\"36F362A3-3AF8-4C36-8740-5536668EE2D8\",\"AppTypeId\":1,\"BinaryVersion\":\"5.14.0\",\"DeviceOSVersion\":\"8.2\",\"MMMInfo\":\"iPhone5,1\"},\"BeaconData\":null,\"UserActionData\":null,\"CheckpointData\":{\"Type\":\"seamlessloginsuccess\"},\"ErrorData\":null,\"ContextData\":null,\"Metadata\":null}","environment":"prod","app":"api","source":"trace","region":"us","hostname":"P-API-02","MetricTypeId":6,"GlobalUserId":null,"ApplicationId":null,"AnonymousId":"36f362a3-3af8-4c36-8740-5536668ee2d8","ViewData":null,"SessionData":{"DeviceId":"36F362A3-3AF8-4C36-8740-5536668EE2D8","AppTypeId":1,"BinaryVersion":"5.14.0","DeviceOSVersion":"8.2","MMMInfo":"iPhone5,1"},"BeaconData":null,"UserActionData":null,"CheckpointData":{"Type":"seamlessloginsuccess"},"ErrorData":null,"ContextData":null,"Metadata":null,"hostip":"10.208.193.153"},"sort":[1434973795000]}]}}